howso/openapi/LICENSE-3RD-PARTY.txt
howso/openapi/__init__.py
howso/openapi/api_client.py
howso/openapi/configuration.py
howso/openapi/exceptions.py
howso/openapi/requirements-3.10.txt
howso/openapi/requirements-3.11.txt
howso/openapi/requirements-3.8.txt
howso/openapi/requirements-3.9.txt
howso/openapi/requirements-dev-3.10.txt
howso/openapi/requirements-dev-3.11.txt
howso/openapi/requirements-dev-3.8.txt
howso/openapi/requirements-dev-3.9.txt
howso/openapi/requirements-dev.in
howso/openapi/requirements.in
howso/openapi/rest.py
howso/openapi/api/__init__.py
howso/openapi/api/account_api.py
howso/openapi/api/information_api.py
howso/openapi/api/project_management_api.py
howso/openapi/api/session_management_api.py
howso/openapi/api/task_operations_api.py
howso/openapi/api/trainee_case_operations_api.py
howso/openapi/api/trainee_feature_operations_api.py
howso/openapi/api/trainee_management_api.py
howso/openapi/api/trainee_metrics_api.py
howso/openapi/api/trainee_operations_api.py
howso/openapi/api/trainee_session_management_api.py
howso/openapi/api/trainee_status_api.py
howso/openapi/models/__init__.py
howso/openapi/models/account.py
howso/openapi/models/account_identity.py
howso/openapi/models/analyze_request.py
howso/openapi/models/api_version.py
howso/openapi/models/append_to_series_store_request.py
howso/openapi/models/async_action.py
howso/openapi/models/async_action_accepted.py
howso/openapi/models/async_action_accepted_tracking.py
howso/openapi/models/async_action_cancel.py
howso/openapi/models/async_action_cancelled_output.py
howso/openapi/models/async_action_complete_output.py
howso/openapi/models/async_action_failed_output.py
howso/openapi/models/async_action_output.py
howso/openapi/models/async_action_status.py
howso/openapi/models/auto_ablation_params.py
howso/openapi/models/base_async_action_output.py
howso/openapi/models/base_react_request.py
howso/openapi/models/begin_session_request.py
howso/openapi/models/boolean_type.py
howso_openapi_client-37.0.4.dist-info/LICENSE.txt
howso_openapi_client-37.0.4.dist-info/METADATA
howso_openapi_client-37.0.4.dist-info/WHEEL
howso_openapi_client-37.0.4.dist-info/top_level.txt
howso_openapi_client-37.0.4.dist-info/RECORD
