Metadata-Version: 2.1
Name: howso-openapi-client
Version: 37.0.4
Summary: Howso OpenAPI
Home-page: 
Author: Howso Incorporated
Author-email: support@howso.com
Keywords: OpenAPI,OpenAPI-Generator,Howso API
Classifier: Development Status :: 3 - Alpha
Classifier: Intended Audience :: Science/Research
Classifier: Topic :: Scientific/Engineering :: Artificial Intelligence
Classifier: License :: OSI Approved :: GNU Affero General Public License v3
Classifier: Programming Language :: Python :: 3
Classifier: Programming Language :: Python :: 3.8
Classifier: Programming Language :: Python :: 3.9
Classifier: Programming Language :: Python :: 3.10
Classifier: Programming Language :: Python :: 3.11
Classifier: Operating System :: MacOS
Classifier: Operating System :: MacOS :: MacOS X
Classifier: Operating System :: Microsoft :: Windows
Classifier: Operating System :: Microsoft :: Windows :: Windows 10
Classifier: Operating System :: Microsoft :: Windows :: Windows 11
Classifier: Operating System :: POSIX :: Linux
License-File: LICENSE.txt
Requires-Dist: six >=1.10
Requires-Dist: python-dateutil >=2.5.3
Requires-Dist: setuptools >=21.0.0
Requires-Dist: urllib3 <3.0,>=1.26.2
Requires-Dist: future ; python_version <= "2.7"
